epmp_igen_document_search_mcp_server/__init__.py
epmp_igen_document_search_mcp_server/api.py
epmp_igen_document_search_mcp_server/options.py
epmp_igen_document_search_mcp_server/tools.py
epmp_igen_document_search_mcp_server-0.2.1.dist-info/WHEEL
epmp_igen_document_search_mcp_server-0.2.1.dist-info/entry_points.txt
epmp_igen_document_search_mcp_server-0.2.1.dist-info/METADATA
epmp_igen_document_search_mcp_server-0.2.1.dist-info/RECORD
