Metadata-Version: 2.3
Name: epmp-igen-document-search-mcp-server
Version: 0.2.1
Summary: InfoNgen search MCP server
Author: Mikita Demidtchik
Author-email: Mikita Demidtchik <mikita_demidtchik@epam.com>
Requires-Dist: mcp[cli]>=1.24.0
Requires-Dist: requests>=2.31.0
Requires-Dist: requests-oauth2client>=1.5.0
Requires-Python: >=3.11
